{
  "coins": [
    {
      "id": "bitcoin",
      "symbol": "BTC",
      "name": "Bitcoin",
      "current_price": 109480,
      "market_cap": 2180659733332,
      "market_cap_rank": 1,
      "total_volume": 36026673330,
      "price_change_percentage_24h": -2.25388,
      "image": "https://coin-images.coingecko.com/coins/images/1/large/bitcoin.png?1696501400",
      "last_updated": "2025-09-04T16:27:43.609Z"
    },
    {
      "id": "ethereum",
      "symbol": "ETH",
      "name": "Ethereum",
      "current_price": 4292.29,
      "market_cap": 518163870886,
      "market_cap_rank": 2,
      "total_volume": 30208062664,
      "price_change_percentage_24h": -3.72944,
      "image": "https://coin-images.coingecko.com/coins/images/279/large/ethereum.png?1696501628",
      "last_updated": "2025-09-04T16:27:44.253Z"
    },
    {
      "id": "tether",
      "symbol": "USDT",
      "name": "Tether",
      "current_price": 1.0,
      "market_cap": 168339279826,
      "market_cap_rank": 3,
      "total_volume": 73494847921,
      "price_change_percentage_24h": -0.00596,
      "image": "https://coin-images.coingecko.com/coins/images/325/large/Tether.png?1696501661",
      "last_updated": "2025-09-04T16:27:49.548Z"
    },
    {
      "id": "ripple",
      "symbol": "XRP",
      "name": "XRP",
      "current_price": 2.81,
      "market_cap": 167245462091,
      "market_cap_rank": 4,
      "total_volume": 4564359786,
      "price_change_percentage_24h": -1.91497,
      "image": "https://coin-images.coingecko.com/coins/images/44/large/xrp-symbol-white-128.png?1696501442",
      "last_updated": "2025-09-04T16:27:49.467Z"
    },
    {
      "id": "binancecoin",
      "symbol": "BNB",
      "name": "BNB",
      "current_price": 844.66,
      "market_cap": 117595122248,
      "market_cap_rank": 5,
      "total_volume": 946702365,
      "price_change_percentage_24h": -1.72335,
      "image": "https://coin-images.coingecko.com/coins/images/825/large/bnb-icon2_2x.png?1696501970",
      "last_updated": "2025-09-04T16:27:49.349Z"
    },
    {
      "id": "solana",
      "symbol": "SOL",
      "name": "Solana",
      "current_price": 203.83,
      "market_cap": 110300647763,
      "market_cap_rank": 6,
      "total_volume": 5024310227,
      "price_change_percentage_24h": -3.24755,
      "image": "https://coin-images.coingecko.com/coins/images/4128/large/solana.png?1718769756",
      "last_updated": "2025-09-04T16:27:49.274Z"
    },
    {
      "id": "usd-coin",
      "symbol": "USDC",
      "name": "USDC",
      "current_price": 0.999794,
      "market_cap": 72585515245,
      "market_cap_rank": 7,
      "total_volume": 11966855912,
      "price_change_percentage_24h": -0.00148,
      "image": "https://coin-images.coingecko.com/coins/images/6319/large/usdc.png?1696506694",
      "last_updated": "2025-09-04T16:27:49.609Z"
    },
    {
      "id": "staked-ether",
      "symbol": "STETH",
      "name": "Lido Staked Ether",
      "current_price": 4286.68,
      "market_cap": 37247432572,
      "market_cap_rank": 8,
      "total_volume": 60050100,
      "price_change_percentage_24h": -3.70777,
      "image": "https://coin-images.coingecko.com/coins/images/13442/large/steth_logo.png?1696513206",
      "last_updated": "2025-09-04T16:27:48.933Z"
    },
    {
      "id": "dogecoin",
      "symbol": "DOGE",
      "name": "Dogecoin",
      "current_price": 0.21233,
      "market_cap": 32022050922,
      "market_cap_rank": 9,
      "total_volume": 1522556068,
      "price_change_percentage_24h": -2.79486,
      "image": "https://coin-images.coingecko.com/coins/images/5/large/dogecoin.png?1696501409",
      "last_updated": "2025-09-04T16:27:49.308Z"
    },
    {
      "id": "tron",
      "symbol": "TRX",
      "name": "TRON",
      "current_price": 0.33536,
      "market_cap": 31749544089,
      "market_cap_rank": 10,
      "total_volume": 644077068,
      "price_change_percentage_24h": -1.6543,
      "image": "https://coin-images.coingecko.com/coins/images/1094/large/tron-logo.png?1696502193",
      "last_updated": "2025-09-04T16:27:49.224Z"
    },
    {
      "id": "cardano",
      "symbol": "ADA",
      "name": "Cardano",
      "current_price": 0.807895,
      "market_cap": 29534917872,
      "market_cap_rank": 11,
      "total_volume": 1101455367,
      "price_change_percentage_24h": -3.78178,
      "image": "https://coin-images.coingecko.com/coins/images/975/large/cardano.png?1696502090",
      "last_updated": "2025-09-04T16:27:49.489Z"
    },
    {
      "id": "wrapped-steth",
      "symbol": "WSTETH",
      "name": "Wrapped stETH",
      "current_price": 5205.71,
      "market_cap": 16406432165,
      "market_cap_rank": 12,
      "total_volume": 86408792,
      "price_change_percentage_24h": -3.61705,
      "image": "https://coin-images.coingecko.com/coins/images/18834/large/wstETH.png?1696518295",
      "last_updated": "2025-09-04T16:27:49.025Z"
    },
    {
      "id": "chainlink",
      "symbol": "LINK",
      "name": "Chainlink",
      "current_price": 22.46,
      "market_cap": 15240046330,
      "market_cap_rank": 13,
      "total_volume": 783817166,
      "price_change_percentage_24h": -5.56863,
      "image": "https://coin-images.coingecko.com/coins/images/877/large/chainlink-new-logo.png?1696502009",
      "last_updated": "2025-09-04T16:27:49.401Z"
    },
    {
      "id": "wrapped-bitcoin",
      "symbol": "WBTC",
      "name": "Wrapped Bitcoin",
      "current_price": 109414,
      "market_cap": 13923567061,
      "market_cap_rank": 15,
      "total_volume": 296659572,
      "price_change_percentage_24h": -2.28138,
      "image": "https://coin-images.coingecko.com/coins/images/7598/large/wrapped_bitcoin_wbtc.png?1696507857",
      "last_updated": "2025-09-04T16:27:49.559Z"
    },
    {
      "id": "ethena-usde",
      "symbol": "USDE",
      "name": "Ethena USDe",
      "current_price": 1.0,
      "market_cap": 12582869850,
      "market_cap_rank": 16,
      "total_volume": 212662543,
      "price_change_percentage_24h": 0.02689,
      "image": "https://coin-images.coingecko.com/coins/images/33613/large/usde.png?1733810059",
      "last_updated": "2025-09-04T16:27:48.983Z"
    },
    {
      "id": "hyperliquid",
      "symbol": "HYPE",
      "name": "Hyperliquid",
      "current_price": 45.07,
      "market_cap": 12205253124,
      "market_cap_rank": 17,
      "total_volume": 294074783,
      "price_change_percentage_24h": -1.91713,
      "image": "https://coin-images.coingecko.com/coins/images/50882/large/hyperliquid.jpg?1729431300",
      "last_updated": "2025-09-04T16:27:48.980Z"
    },
    {
      "id": "bitcoin-cash",
      "symbol": "BCH",
      "name": "Bitcoin Cash",
      "current_price": 587.51,
      "market_cap": 11706574015,
      "market_cap_rank": 19,
      "total_volume": 337278392,
      "price_change_percentage_24h": -0.63771,
      "image": "https://coin-images.coingecko.com/coins/images/780/large/bitcoin-cash-circle.png?1696501932",
      "last_updated": "2025-09-04T16:27:49.275Z"
    },
    {
      "id": "sui",
      "symbol": "SUI",
      "name": "Sui",
      "current_price": 3.26,
      "market_cap": 11647204611,
      "market_cap_rank": 20,
      "total_volume": 693075999,
      "price_change_percentage_24h": -3.56801,
      "image": "https://coin-images.coingecko.com/coins/images/26375/large/sui-ocean-square.png?1727791290",
      "last_updated": "2025-09-04T16:27:49.681Z"
    },
    {
      "id": "wrapped-eeth",
      "symbol": "WEETH",
      "name": "Wrapped eETH",
      "current_price": 4611.58,
      "market_cap": 11609441797,
      "market_cap_rank": 21,
      "total_volume": 29605893,
      "price_change_percentage_24h": -3.6047,
      "image": "https://coin-images.coingecko.com/coins/images/33033/large/weETH.png?1701438396",
      "last_updated": "2025-09-04T16:27:49.074Z"
    },
    {
      "id": "stellar",
      "symbol": "XLM",
      "name": "Stellar",
      "current_price": 0.354167,
      "market_cap": 11230922486,
      "market_cap_rank": 22,
      "total_volume": 163972825,
      "price_change_percentage_24h": -3.02209,
      "image": "https://coin-images.coingecko.com/coins/images/100/large/fmpFRHHQ_400x400.jpg?1735231350",
      "last_updated": "2025-09-04T16:27:49.337Z"
    },
    {
      "id": "avalanche-2",
      "symbol": "AVAX",
      "name": "Avalanche",
      "current_price": 24.68,
      "market_cap": 10423286798,
      "market_cap_rank": 23,
      "total_volume": 484022118,
      "price_change_percentage_24h": -2.73581,
      "image": "https://coin-images.coingecko.com/coins/images/12559/large/Avalanche_Circle_RedWhite_Trans.png?1696512369",
      "last_updated": "2025-09-04T16:27:49.261Z"
    },
    {
      "id": "hedera-hashgraph",
      "symbol": "HBAR",
      "name": "Hedera",
      "current_price": 0.212004,
      "market_cap": 8986455597,
      "market_cap_rank": 25,
      "total_volume": 210806057,
      "price_change_percentage_24h": -4.15826,
      "image": "https://coin-images.coingecko.com/coins/images/3688/large/hbar.png?1696504364",
      "last_updated": "2025-09-04T16:27:49.065Z"
    },
    {
      "id": "crypto-com-chain",
      "symbol": "CRO",
      "name": "Cronos",
      "current_price": 0.266296,
      "market_cap": 8951594738,
      "market_cap_rank": 26,
      "total_volume": 320888863,
      "price_change_percentage_24h": -4.32384,
      "image": "https://coin-images.coingecko.com/coins/images/7310/large/cro_token_logo.png?1696507599",
      "last_updated": "2025-09-04T16:27:49.045Z"
    },
    {
      "id": "litecoin",
      "symbol": "LTC",
      "name": "Litecoin",
      "current_price": 109.93,
      "market_cap": 8386756149,
      "market_cap_rank": 28,
      "total_volume": 395842950,
      "price_change_percentage_24h": -2.5747,
      "image": "https://coin-images.coingecko.com/coins/images/2/large/litecoin.png?1696501400",
      "last_updated": "2025-09-04T16:27:49.357Z"
    },
    {
      "id": "the-open-network",
      "symbol": "TON",
      "name": "Toncoin",
      "current_price": 3.1,
      "market_cap": 7976720654,
      "market_cap_rank": 30,
      "total_volume": 134094763,
      "price_change_percentage_24h": -2.41836,
      "image": "https://coin-images.coingecko.com/coins/images/17980/large/photo_2024-09-10_17.09.00.jpeg?1725963446",
      "last_updated": "2025-09-04T16:27:50.156Z"
    },
    {
      "id": "shiba-inu",
      "symbol": "SHIB",
      "name": "Shiba Inu",
      "current_price": 1.209e-05,
      "market_cap": 7124793234,
      "market_cap_rank": 31,
      "total_volume": 146611495,
      "price_change_percentage_24h": -3.47678,
      "image": "https://coin-images.coingecko.com/coins/images/11939/large/shiba.png?1696511800",
      "last_updated": "2025-09-04T16:27:49.173Z"
    },
    {
      "id": "binance-bridged-usdt-bnb-smart-chain",
      "symbol": "BSC-USD",
      "name": "Binance Bridged USDT (BNB Smart Chain)",
      "current_price": 0.99988,
      "market_cap": 6785061643,
      "market_cap_rank": 32,
      "total_volume": 1874660247,
      "price_change_percentage_24h": 0.00426,
      "image": "https://coin-images.coingecko.com/coins/images/35021/large/USDT.png?1707233575",
      "last_updated": "2025-09-04T16:27:49.764Z"
    },
    {
      "id": "coinbase-wrapped-btc",
      "symbol": "CBBTC",
      "name": "Coinbase Wrapped BTC",
      "current_price": 109467,
      "market_cap": 6123292598,
      "market_cap_rank": 33,
      "total_volume": 368283074,
      "price_change_percentage_24h": -2.26806,
      "image": "https://coin-images.coingecko.com/coins/images/40143/large/cbbtc.webp?1726136727",
      "last_updated": "2025-09-04T16:27:49.409Z"
    },
    {
      "id": "whitebit",
      "symbol": "WBT",
      "name": "WhiteBIT Coin",
      "current_price": 41.96,
      "market_cap": 6052443185,
      "market_cap_rank": 34,
      "total_volume": 43801158,
      "price_change_percentage_24h": -2.95077,
      "image": "https://coin-images.coingecko.com/coins/images/27045/large/wbt_token.png?1696526096",
      "last_updated": "2025-09-04T16:27:49.049Z"
    },
    {
      "id": "polkadot",
      "symbol": "DOT",
      "name": "Polkadot",
      "current_price": 3.76,
      "market_cap": 5732957683,
      "market_cap_rank": 35,
      "total_volume": 168131276,
      "price_change_percentage_24h": -3.1076,
      "image": "https://coin-images.coingecko.com/coins/images/12171/large/polkadot.png?1696512008",
      "last_updated": "2025-09-04T16:27:50.084Z"
    },
    {
      "id": "ethena-staked-usde",
      "symbol": "SUSDE",
      "name": "Ethena Staked USDe",
      "current_price": 1.19,
      "market_cap": 5655591728,
      "market_cap_rank": 36,
      "total_volume": 48052758,
      "price_change_percentage_24h": 0.03398,
      "image": "https://coin-images.coingecko.com/coins/images/33669/large/sUSDe-Symbol-Color.png?1716307680",
      "last_updated": "2025-09-04T16:27:49.043Z"
    },
    {
      "id": "uniswap",
      "symbol": "UNI",
      "name": "Uniswap",
      "current_price": 9.2,
      "market_cap": 5529948795,
      "market_cap_rank": 37,
      "total_volume": 288556287,
      "price_change_percentage_24h": -5.3103,
      "image": "https://coin-images.coingecko.com/coins/images/12504/large/uniswap-logo.png?1720676669",
      "last_updated": "2025-09-04T16:27:49.840Z"
    },
    {
      "id": "monero",
      "symbol": "XMR",
      "name": "Monero",
      "current_price": 269.45,
      "market_cap": 4972873919,
      "market_cap_rank": 38,
      "total_volume": 66157776,
      "price_change_percentage_24h": 0.06441,
      "image": "https://coin-images.coingecko.com/coins/images/69/large/monero_logo.png?1696501460",
      "last_updated": "2025-09-04T16:27:49.769Z"
    },
    {
      "id": "world-liberty-financial",
      "symbol": "WLFI",
      "name": "World Liberty Financial",
      "current_price": 0.174769,
      "market_cap": 4777123626,
      "market_cap_rank": 39,
      "total_volume": 1241011430,
      "price_change_percentage_24h": -20.21609,
      "image": "https://coin-images.coingecko.com/coins/images/50767/large/wlfi.png?1756438915",
      "last_updated": "2025-09-04T16:27:49.278Z"
    },
    {
      "id": "aave",
      "symbol": "AAVE",
      "name": "Aave",
      "current_price": 308.56,
      "market_cap": 4700052795,
      "market_cap_rank": 40,
      "total_volume": 546644488,
      "price_change_percentage_24h": -5.3678,
      "image": "https://coin-images.coingecko.com/coins/images/12645/large/aave-token-round.png?1720472354",
      "last_updated": "2025-09-04T16:27:50.089Z"
    },
    {
      "id": "bitget-token",
      "symbol": "BGB",
      "name": "Bitget Token",
      "current_price": 4.84,
      "market_cap": 4451076581,
      "market_cap_rank": 43,
      "total_volume": 239767386,
      "price_change_percentage_24h": -2.35525,
      "image": "https://coin-images.coingecko.com/coins/images/11610/large/Bitget_logo.png?1736925727",
      "last_updated": "2025-09-04T16:27:49.374Z"
    },
    {
      "id": "ethena",
      "symbol": "ENA",
      "name": "Ethena",
      "current_price": 0.66595,
      "market_cap": 4431853210,
      "market_cap_rank": 42,
      "total_volume": 540871495,
      "price_change_percentage_24h": -8.49873,
      "image": "https://coin-images.coingecko.com/coins/images/36530/large/ethena.png?1711701436",
      "last_updated": "2025-09-04T16:27:49.166Z"
    },
    {
      "id": "pepe",
      "symbol": "PEPE",
      "name": "Pepe",
      "current_price": 9.43e-06,
      "market_cap": 3970838961,
      "market_cap_rank": 44,
      "total_volume": 366317213,
      "price_change_percentage_24h": -4.70702,
      "image": "https://coin-images.coingecko.com/coins/images/29850/large/pepe-token.jpeg?1696528776",
      "last_updated": "2025-09-04T16:27:49.789Z"
    },
    {
      "id": "mantle",
      "symbol": "MNT",
      "name": "Mantle",
      "current_price": 1.14,
      "market_cap": 3705373335,
      "market_cap_rank": 45,
      "total_volume": 287321435,
      "price_change_percentage_24h": 2.3303,
      "image": "https://coin-images.coingecko.com/coins/images/30980/large/Mantle-Logo-mark.png?1739213200",
      "last_updated": "2025-09-04T16:27:49.191Z"
    },
    {
      "id": "okb",
      "symbol": "OKB",
      "name": "OKB",
      "current_price": 175.82,
      "market_cap": 3692816354,
      "market_cap_rank": 46,
      "total_volume": 188923925,
      "price_change_percentage_24h": -2.89005,
      "image": "https://coin-images.coingecko.com/coins/images/4463/large/WeChat_Image_20220118095654.png?1696505053",
      "last_updated": "2025-09-04T16:27:50.072Z"
    },
    {
      "id": "ethereum-classic",
      "symbol": "ETC",
      "name": "Ethereum Classic",
      "current_price": 20.14,
      "market_cap": 3089488261,
      "market_cap_rank": 47,
      "total_volume": 67189036,
      "price_change_percentage_24h": -4.1062,
      "image": "https://coin-images.coingecko.com/coins/images/453/large/ethereum-classic-logo.png?1696501717",
      "last_updated": "2025-09-04T16:27:49.483Z"
    },
    {
      "id": "jito-staked-sol",
      "symbol": "JITOSOL",
      "name": "Jito Staked SOL",
      "current_price": 250.36,
      "market_cap": 3014941587,
      "market_cap_rank": 48,
      "total_volume": 37511490,
      "price_change_percentage_24h": -2.76388,
      "image": "https://coin-images.coingecko.com/coins/images/28046/large/JitoSOL-200.png?1696527060",
      "last_updated": "2025-09-04T16:27:49.169Z"
    },
    {
      "id": "bittensor",
      "symbol": "TAO",
      "name": "Bittensor",
      "current_price": 312.62,
      "market_cap": 3002096682,
      "market_cap_rank": 49,
      "total_volume": 52023722,
      "price_change_percentage_24h": -4.03902,
      "image": "https://coin-images.coingecko.com/coins/images/28452/large/ARUsPeNQ_400x400.jpeg?1696527447",
      "last_updated": "2025-09-04T16:27:49.132Z"
    },
    {
      "id": "near",
      "symbol": "NEAR",
      "name": "NEAR Protocol",
      "current_price": 2.38,
      "market_cap": 2974125870,
      "market_cap_rank": 50,
      "total_volume": 106208429,
      "price_change_percentage_24h": -3.94509,
      "image": "https://coin-images.coingecko.com/coins/images/10365/large/near.jpg?1696510367",
      "last_updated": "2025-09-04T16:27:49.264Z"
    },
    {
      "id": "polygon-ecosystem-token",
      "symbol": "POL",
      "name": "POL (ex-MATIC)",
      "current_price": 0.279244,
      "market_cap": 2935500595,
      "market_cap_rank": 51,
      "total_volume": 176358197,
      "price_change_percentage_24h": -1.78245,
      "image": "https://coin-images.coingecko.com/coins/images/32440/large/polygon.png?1698233684",
      "last_updated": "2025-09-04T16:27:49.267Z"
    },
    {
      "id": "aptos",
      "symbol": "APT",
      "name": "Aptos",
      "current_price": 4.22,
      "market_cap": 2907487181,
      "market_cap_rank": 52,
      "total_volume": 329246345,
      "price_change_percentage_24h": -3.42411,
      "image": "https://coin-images.coingecko.com/coins/images/26455/large/aptos_round.png?1696525528",
      "last_updated": "2025-09-04T16:27:49.434Z"
    },
    {
      "id": "ondo-finance",
      "symbol": "ONDO",
      "name": "Ondo",
      "current_price": 0.909943,
      "market_cap": 2878617986,
      "market_cap_rank": 53,
      "total_volume": 159705641,
      "price_change_percentage_24h": -6.04098,
      "image": "https://coin-images.coingecko.com/coins/images/26580/large/ONDO.png?1696525656",
      "last_updated": "2025-09-04T16:27:49.264Z"
    },
    {
      "id": "usdt0",
      "symbol": "USDT0",
      "name": "USDT0",
      "current_price": 1.001,
      "market_cap": 2784728377,
      "market_cap_rank": 54,
      "total_volume": 312787316,
      "price_change_percentage_24h": -0.00278,
      "image": "https://coin-images.coingecko.com/coins/images/53705/large/usdt0.jpg?1737086183",
      "last_updated": "2025-09-04T16:27:49.656Z"
    },
    {
      "id": "pi-network",
      "symbol": "PI",
      "name": "Pi Network",
      "current_price": 0.342648,
      "market_cap": 2743127599,
      "market_cap_rank": 55,
      "total_volume": 46097934,
      "price_change_percentage_24h": -2.80269,
      "image": "https://coin-images.coingecko.com/coins/images/54342/large/pi_network.jpg?1739347576",
      "last_updated": "2025-09-04T16:27:49.542Z"
    },
    {
      "id": "usd1-wlfi",
      "symbol": "USD1",
      "name": "USD1",
      "current_price": 0.999088,
      "market_cap": 2644325167,
      "market_cap_rank": 56,
      "total_volume": 343768956,
      "price_change_percentage_24h": -0.05976,
      "image": "https://coin-images.coingecko.com/coins/images/54977/large/USD1_1000x1000_transparent.png?1749297002",
      "last_updated": "2025-09-04T16:27:49.477Z"
    },
    {
      "id": "binance-peg-weth",
      "symbol": "WETH",
      "name": "Binance-Peg WETH",
      "current_price": 4296.13,
      "market_cap": 2601431557,
      "market_cap_rank": 57,
      "total_volume": 64950377,
      "price_change_percentage_24h": -3.72553,
      "image": "https://coin-images.coingecko.com/coins/images/39580/large/weth.png?1723006716",
      "last_updated": "2025-09-04T16:27:50.323Z"
    },
    {
      "id": "arbitrum",
      "symbol": "ARB",
      "name": "Arbitrum",
      "current_price": 0.484475,
      "market_cap": 2566081035,
      "market_cap_rank": 58,
      "total_volume": 251990680,
      "price_change_percentage_24h": -6.22575,
      "image": "https://coin-images.coingecko.com/coins/images/16547/large/arb.jpg?1721358242",
      "last_updated": "2025-09-04T16:27:49.777Z"
    },
    {
      "id": "internet-computer",
      "symbol": "ICP",
      "name": "Internet Computer",
      "current_price": 4.73,
      "market_cap": 2542518171,
      "market_cap_rank": 59,
      "total_volume": 45585645,
      "price_change_percentage_24h": -3.07012,
      "image": "https://coin-images.coingecko.com/coins/images/14495/large/Internet_Computer_logo.png?1696514180",
      "last_updated": "2025-09-04T16:27:49.706Z"
    },
    {
      "id": "story-2",
      "symbol": "IP",
      "name": "Story",
      "current_price": 7.91,
      "market_cap": 2410248455,
      "market_cap_rank": 60,
      "total_volume": 162115358,
      "price_change_percentage_24h": -2.74771,
      "image": "https://coin-images.coingecko.com/coins/images/54035/large/Transparent_bg.png?1738075331",
      "last_updated": "2025-09-04T16:27:49.458Z"
    },
    {
      "id": "kaspa",
      "symbol": "KAS",
      "name": "Kaspa",
      "current_price": 0.081714,
      "market_cap": 2156145771,
      "market_cap_rank": 64,
      "total_volume": 21152115,
      "price_change_percentage_24h": -3.89926,
      "image": "https://coin-images.coingecko.com/coins/images/25751/large/kaspa-icon-exchanges.png?1696524837",
      "last_updated": "2025-09-04T16:27:50.078Z"
    },
    {
      "id": "cosmos",
      "symbol": "ATOM",
      "name": "Cosmos Hub",
      "current_price": 4.39,
      "market_cap": 2050312769,
      "market_cap_rank": 65,
      "total_volume": 77210595,
      "price_change_percentage_24h": -3.53334,
      "image": "https://coin-images.coingecko.com/coins/images/1481/large/cosmos_hub.png?1696502525",
      "last_updated": "2025-09-04T16:27:49.577Z"
    },
    {
      "id": "susds",
      "symbol": "SUSDS",
      "name": "sUSDS",
      "current_price": 1.066,
      "market_cap": 2020470166,
      "market_cap_rank": 66,
      "total_volume": 27487456,
      "price_change_percentage_24h": 0.21749,
      "image": "https://coin-images.coingecko.com/coins/images/52721/large/sUSDS_Coin.png?1734086971",
      "last_updated": "2025-09-04T16:27:49.438Z"
    },
    {
      "id": "jupiter-perpetuals-liquidity-provider-token",
      "symbol": "JLP",
      "name": "Jupiter Perpetuals Liquidity Provider Token",
      "current_price": 5.41,
      "market_cap": 2006246974,
      "market_cap_rank": 68,
      "total_volume": 70595810,
      "price_change_percentage_24h": -1.57279,
      "image": "https://coin-images.coingecko.com/coins/images/33094/large/jlp.png?1700631386",
      "last_updated": "2025-09-04T16:27:49.229Z"
    },
    {
      "id": "vechain",
      "symbol": "VET",
      "name": "VeChain",
      "current_price": 0.02314258,
      "market_cap": 1990880737,
      "market_cap_rank": 69,
      "total_volume": 28516418,
      "price_change_percentage_24h": -3.63598,
      "image": "https://coin-images.coingecko.com/coins/images/1167/large/VET.png?1742383283",
      "last_updated": "2025-09-04T16:27:49.953Z"
    },
    {
      "id": "algorand",
      "symbol": "ALGO",
      "name": "Algorand",
      "current_price": 0.225828,
      "market_cap": 1973960754,
      "market_cap_rank": 70,
      "total_volume": 56300732,
      "price_change_percentage_24h": -3.94523,
      "image": "https://coin-images.coingecko.com/coins/images/4380/large/download.png?1696504978",
      "last_updated": "2025-09-04T16:27:49.362Z"
    },
    {
      "id": "fasttoken",
      "symbol": "FTN",
      "name": "Fasttoken",
      "current_price": 4.5,
      "market_cap": 1942966096,
      "market_cap_rank": 72,
      "total_volume": 58097330,
      "price_change_percentage_24h": -0.24558,
      "image": "https://coin-images.coingecko.com/coins/images/28478/large/lightenicon_200x200.png?1696527472",
      "last_updated": "2025-09-04T16:27:49.224Z"
    },
    {
      "id": "pudgy-penguins",
      "symbol": "PENGU",
      "name": "Pudgy Penguins",
      "current_price": 0.02853544,
      "market_cap": 1798001452,
      "market_cap_rank": 74,
      "total_volume": 194864106,
      "price_change_percentage_24h": -7.12222,
      "image": "https://coin-images.coingecko.com/coins/images/52622/large/PUDGY_PENGUINS_PENGU_PFP.png?1733809110",
      "last_updated": "2025-09-04T16:27:49.519Z"
    },
    {
      "id": "worldcoin-wld",
      "symbol": "WLD",
      "name": "Worldcoin",
      "current_price": 0.864962,
      "market_cap": 1734726982,
      "market_cap_rank": 76,
      "total_volume": 109098154,
      "price_change_percentage_24h": -3.86992,
      "image": "https://coin-images.coingecko.com/coins/images/31069/large/worldcoin.jpeg?1696529903",
      "last_updated": "2025-09-04T16:27:50.308Z"
    },
    {
      "id": "render-token",
      "symbol": "RENDER",
      "name": "Render",
      "current_price": 3.34,
      "market_cap": 1731669471,
      "market_cap_rank": 77,
      "total_volume": 40691151,
      "price_change_percentage_24h": -4.94486,
      "image": "https://coin-images.coingecko.com/coins/images/11636/large/rndr.png?1696511529",
      "last_updated": "2025-09-04T16:27:49.492Z"
    },
    {
      "id": "sei-network",
      "symbol": "SEI",
      "name": "Sei",
      "current_price": 0.279341,
      "market_cap": 1680014554,
      "market_cap_rank": 80,
      "total_volume": 119606741,
      "price_change_percentage_24h": -4.85068,
      "image": "https://coin-images.coingecko.com/coins/images/28205/large/Sei_Logo_-_Transparent.png?1696527207",
      "last_updated": "2025-09-04T16:27:49.335Z"
    },
    {
      "id": "kinetic-staked-hype",
      "symbol": "KHYPE",
      "name": "Kinetiq Staked HYPE",
      "current_price": 45.2,
      "market_cap": 1674126122,
      "market_cap_rank": 81,
      "total_volume": 61622522,
      "price_change_percentage_24h": -1.98064,
      "image": "https://coin-images.coingecko.com/coins/images/67388/large/khype.png?1752632397",
      "last_updated": "2025-09-04T16:27:49.562Z"
    },
    {
      "id": "official-trump",
      "symbol": "TRUMP",
      "name": "Official Trump",
      "current_price": 8.24,
      "market_cap": 1647787772,
      "market_cap_rank": 82,
      "total_volume": 209788871,
      "price_change_percentage_24h": -2.28267,
      "image": "https://coin-images.coingecko.com/coins/images/53746/large/trump.png?1737171561",
      "last_updated": "2025-09-04T16:27:49.878Z"
    },
    {
      "id": "fetch-ai",
      "symbol": "FET",
      "name": "Artificial Superintelligence Alliance",
      "current_price": 0.592079,
      "market_cap": 1543486424,
      "market_cap_rank": 87,
      "total_volume": 50393626,
      "price_change_percentage_24h": -5.06866,
      "image": "https://coin-images.coingecko.com/coins/images/5681/large/ASI.png?1719827289",
      "last_updated": "2025-09-04T16:27:49.601Z"
    },
    {
      "id": "filecoin",
      "symbol": "FIL",
      "name": "Filecoin",
      "current_price": 2.24,
      "market_cap": 1539290903,
      "market_cap_rank": 88,
      "total_volume": 136762832,
      "price_change_percentage_24h": -3.70245,
      "image": "https://coin-images.coingecko.com/coins/images/12817/large/filecoin.png?1696512609",
      "last_updated": "2025-09-04T16:27:49.597Z"
    },
    {
      "id": "jupiter-exchange-solana",
      "symbol": "JUP",
      "name": "Jupiter",
      "current_price": 0.480253,
      "market_cap": 1495797696,
      "market_cap_rank": 91,
      "total_volume": 33733477,
      "price_change_percentage_24h": -4.6153,
      "image": "https://coin-images.coingecko.com/coins/images/34188/large/jup.png?1704266489",
      "last_updated": "2025-09-04T16:27:49.934Z"
    },
    {
      "id": "bonk",
      "symbol": "BONK",
      "name": "Bonk",
      "current_price": 1.926e-05,
      "market_cap": 1489921580,
      "market_cap_rank": 93,
      "total_volume": 188009412,
      "price_change_percentage_24h": -6.50169,
      "image": "https://coin-images.coingecko.com/coins/images/28600/large/bonk.jpg?1696527587",
      "last_updated": "2025-09-04T16:27:49.554Z"
    },
    {
      "id": "pump-fun",
      "symbol": "PUMP",
      "name": "Pump.fun",
      "current_price": 0.00419279,
      "market_cap": 1485503897,
      "market_cap_rank": 90,
      "total_volume": 450483766,
      "price_change_percentage_24h": 8.28748,
      "image": "https://coin-images.coingecko.com/coins/images/67164/large/pump.jpg?1751949376",
      "last_updated": "2025-09-04T16:27:49.623Z"
    },
    {
      "id": "polygon-bridged-usdt-polygon",
      "symbol": "USDT",
      "name": "Polygon Bridged USDT (Polygon)",
      "current_price": 1.0,
      "market_cap": 1408432141,
      "market_cap_rank": 95,
      "total_volume": 31283482,
      "price_change_percentage_24h": 0.00441,
      "image": "https://coin-images.coingecko.com/coins/images/35023/large/USDT.png?1707233644",
      "last_updated": "2025-09-04T16:27:49.850Z"
    },
    {
      "id": "four",
      "symbol": "FORM",
      "name": "Four",
      "current_price": 3.68,
      "market_cap": 1401692509,
      "market_cap_rank": 96,
      "total_volume": 37509853,
      "price_change_percentage_24h": 3.07623,
      "image": "https://coin-images.coingecko.com/coins/images/54912/large/four.jpg?1742461445",
      "last_updated": "2025-09-04T16:27:49.459Z"
    },
    {
      "id": "xdce-crowd-sale",
      "symbol": "XDC",
      "name": "XDC Network",
      "current_price": 0.077697,
      "market_cap": 1378354172,
      "market_cap_rank": 97,
      "total_volume": 30608687,
      "price_change_percentage_24h": -1.58206,
      "image": "https://coin-images.coingecko.com/coins/images/2912/large/xdc-icon.png?1696503661",
      "last_updated": "2025-09-04T16:27:49.722Z"
    },
    {
      "id": "tether-gold",
      "symbol": "XAUT",
      "name": "Tether Gold",
      "current_price": 3559.28,
      "market_cap": 1331565691,
      "market_cap_rank": 99,
      "total_volume": 176777825,
      "price_change_percentage_24h": 0.04414,
      "image": "https://coin-images.coingecko.com/coins/images/10481/large/Tether_Gold.png?1696510471",
      "last_updated": "2025-09-04T16:27:50.435Z"
    },
    {
      "id": "injective-protocol",
      "symbol": "INJ",
      "name": "Injective",
      "current_price": 12.56,
      "market_cap": 1227111746,
      "market_cap_rank": 103,
      "total_volume": 80618806,
      "price_change_percentage_24h": -5.71554,
      "image": "https://coin-images.coingecko.com/coins/images/12882/large/Other_200x200.png?1738782212",
      "last_updated": "2025-09-04T16:27:49.860Z"
    },
    {
      "id": "optimism",
      "symbol": "OP",
      "name": "Optimism",
      "current_price": 0.687888,
      "market_cap": 1223513432,
      "market_cap_rank": 104,
      "total_volume": 94503349,
      "price_change_percentage_24h": -4.86837,
      "image": "https://coin-images.coingecko.com/coins/images/25244/large/Optimism.png?1696524385",
      "last_updated": "2025-09-04T16:27:49.772Z"
    },
    {
      "id": "celestia",
      "symbol": "TIA",
      "name": "Celestia",
      "current_price": 1.55,
      "market_cap": 1197136680,
      "market_cap_rank": 105,
      "total_volume": 68358966,
      "price_change_percentage_24h": -5.29778,
      "image": "https://coin-images.coingecko.com/coins/images/31967/large/tia.jpg?1696530772",
      "last_updated": "2025-09-04T16:27:49.638Z"
    },
    {
      "id": "paypal-usd",
      "symbol": "PYUSD",
      "name": "PayPal USD",
      "current_price": 1.0,
      "market_cap": 1177758424,
      "market_cap_rank": 107,
      "total_volume": 43678285,
      "price_change_percentage_24h": -0.03433,
      "image": "https://coin-images.coingecko.com/coins/images/31212/large/PYUSD_Logo_%282%29.png?1696530039",
      "last_updated": "2025-09-04T16:27:49.433Z"
    },
    {
      "id": "first-digital-usd",
      "symbol": "FDUSD",
      "name": "First Digital USD",
      "current_price": 0.998298,
      "market_cap": 1155851250,
      "market_cap_rank": 108,
      "total_volume": 5421337613,
      "price_change_percentage_24h": -0.08159,
      "image": "https://coin-images.coingecko.com/coins/images/31079/large/FDUSD_icon_black.png?1731097953",
      "last_updated": "2025-09-04T16:27:49.684Z"
    },
    {
      "id": "blockstack",
      "symbol": "STX",
      "name": "Stacks",
      "current_price": 0.609643,
      "market_cap": 1095346717,
      "market_cap_rank": 111,
      "total_volume": 26531820,
      "price_change_percentage_24h": -5.04572,
      "image": "https://coin-images.coingecko.com/coins/images/2069/large/Stacks_Logo_png.png?1709979332",
      "last_updated": "2025-09-04T16:27:49.888Z"
    },
    {
      "id": "binance-bridged-usdc-bnb-smart-chain",
      "symbol": "USDC",
      "name": "Binance Bridged USDC (BNB Smart Chain)",
      "current_price": 0.999716,
      "market_cap": 1048815557,
      "market_cap_rank": 112,
      "total_volume": 230643046,
      "price_change_percentage_24h": -0.0012,
      "image": "https://coin-images.coingecko.com/coins/images/35220/large/USDC.jpg?1707919050",
      "last_updated": "2025-09-04T16:27:49.633Z"
    },
    {
      "id": "curve-dao-token",
      "symbol": "CRV",
      "name": "Curve DAO",
      "current_price": 0.744493,
      "market_cap": 1042352491,
      "market_cap_rank": 113,
      "total_volume": 90409644,
      "price_change_percentage_24h": -5.34098,
      "image": "https://coin-images.coingecko.com/coins/images/12124/large/Curve.png?1696511967",
      "last_updated": "2025-09-04T16:27:39.704Z"
    },
    {
      "id": "lido-dao",
      "symbol": "LDO",
      "name": "Lido DAO",
      "current_price": 1.16,
      "market_cap": 1038441625,
      "market_cap_rank": 114,
      "total_volume": 77698876,
      "price_change_percentage_24h": -6.34092,
      "image": "https://coin-images.coingecko.com/coins/images/13573/large/Lido_DAO.png?1696513326",
      "last_updated": "2025-09-04T16:27:49.628Z"
    },
    {
      "id": "pax-gold",
      "symbol": "PAXG",
      "name": "PAX Gold",
      "current_price": 3562.1,
      "market_cap": 1012326874,
      "market_cap_rank": 115,
      "total_volume": 152221634,
      "price_change_percentage_24h": -0.39457,
      "image": "https://coin-images.coingecko.com/coins/images/9519/large/paxgold.png?1696509604",
      "last_updated": "2025-09-04T16:27:49.431Z"
    },
    {
      "id": "spx6900",
      "symbol": "SPX",
      "name": "SPX6900",
      "current_price": 1.082,
      "market_cap": 1009332468,
      "market_cap_rank": 116,
      "total_volume": 21940900,
      "price_change_percentage_24h": -8.09515,
      "image": "https://coin-images.coingecko.com/coins/images/31401/large/centeredcoin_%281%29.png?1737048493",
      "last_updated": "2025-09-04T16:27:49.643Z"
    },
    {
      "id": "syrupusdc",
      "symbol": "SYRUPUSDC",
      "name": "SyrupUSDC",
      "current_price": 1.12,
      "market_cap": 1003356455,
      "market_cap_rank": 117,
      "total_volume": 29039080,
      "price_change_percentage_24h": -0.00545,
      "image": "https://coin-images.coingecko.com/coins/images/54658/large/SyrupUSDCO.png?1748850129",
      "last_updated": "2025-09-04T16:27:49.578Z"
    },
    {
      "id": "aerodrome-finance",
      "symbol": "AERO",
      "name": "Aerodrome Finance",
      "current_price": 1.095,
      "market_cap": 981571763,
      "market_cap_rank": 118,
      "total_volume": 52703257,
      "price_change_percentage_24h": -7.39938,
      "image": "https://coin-images.coingecko.com/coins/images/31745/large/token.png?1696530564",
      "last_updated": "2025-09-04T16:27:49.753Z"
    },
    {
      "id": "arbitrum-bridged-wbtc-arbitrum-one",
      "symbol": "WBTC",
      "name": "Arbitrum Bridged WBTC (Arbitrum One)",
      "current_price": 109409,
      "market_cap": 914761977,
      "market_cap_rank": 124,
      "total_volume": 101435427,
      "price_change_percentage_24h": -2.30594,
      "image": "https://coin-images.coingecko.com/coins/images/39532/large/wbtc.png?1722810336",
      "last_updated": "2025-09-04T16:27:49.685Z"
    },
    {
      "id": "the-graph",
      "symbol": "GRT",
      "name": "The Graph",
      "current_price": 0.086614,
      "market_cap": 907089399,
      "market_cap_rank": 125,
      "total_volume": 27838524,
      "price_change_percentage_24h": -4.32853,
      "image": "https://coin-images.coingecko.com/coins/images/13397/large/Graph_Token.png?1696513159",
      "last_updated": "2025-09-04T16:27:49.895Z"
    },
    {
      "id": "raydium",
      "symbol": "RAY",
      "name": "Raydium",
      "current_price": 3.28,
      "market_cap": 880343007,
      "market_cap_rank": 126,
      "total_volume": 40150458,
      "price_change_percentage_24h": -4.91707,
      "image": "https://coin-images.coingecko.com/coins/images/13928/large/PSigc4ie_400x400.jpg?1696513668",
      "last_updated": "2025-09-04T16:27:49.591Z"
    },
    {
      "id": "conflux-token",
      "symbol": "CFX",
      "name": "Conflux",
      "current_price": 0.168941,
      "market_cap": 867036335,
      "market_cap_rank": 127,
      "total_volume": 42232192,
      "price_change_percentage_24h": -4.63409,
      "image": "https://coin-images.coingecko.com/coins/images/13079/large/3vuYMbjN.png?1696512867",
      "last_updated": "2025-09-04T16:27:49.851Z"
    },
    {
      "id": "floki",
      "symbol": "FLOKI",
      "name": "FLOKI",
      "current_price": 8.82e-05,
      "market_cap": 851877239,
      "market_cap_rank": 129,
      "total_volume": 43458981,
      "price_change_percentage_24h": -5.08104,
      "image": "https://coin-images.coingecko.com/coins/images/16746/large/PNG_image.png?1696516318",
      "last_updated": "2025-09-04T16:27:49.641Z"
    },
    {
      "id": "pyth-network",
      "symbol": "PYTH",
      "name": "Pyth Network",
      "current_price": 0.147698,
      "market_cap": 848731881,
      "market_cap_rank": 131,
      "total_volume": 128695096,
      "price_change_percentage_24h": -7.05747,
      "image": "https://coin-images.coingecko.com/coins/images/31924/large/pyth.png?1701245725",
      "last_updated": "2025-09-04T16:27:49.980Z"
    },
    {
      "id": "l2-standard-bridged-weth-base",
      "symbol": "WETH",
      "name": "L2 Standard Bridged WETH (Base)",
      "current_price": 4298.13,
      "market_cap": 830007302,
      "market_cap_rank": 134,
      "total_volume": 771647572,
      "price_change_percentage_24h": -3.82404,
      "image": "https://coin-images.coingecko.com/coins/images/39810/large/weth.png?1724139790",
      "last_updated": "2025-09-04T16:27:50.378Z"
    },
    {
      "id": "pancakeswap-token",
      "symbol": "CAKE",
      "name": "PancakeSwap",
      "current_price": 2.34,
      "market_cap": 808516862,
      "market_cap_rank": 135,
      "total_volume": 43660508,
      "price_change_percentage_24h": -2.86372,
      "image": "https://coin-images.coingecko.com/coins/images/12632/large/pancakeswap-cake-logo_%281%29.png?1696512440",
      "last_updated": "2025-09-04T16:27:49.848Z"
    },
    {
      "id": "dogwifcoin",
      "symbol": "WIF",
      "name": "dogwifhat",
      "current_price": 0.782166,
      "market_cap": 782081039,
      "market_cap_rank": 136,
      "total_volume": 135701714,
      "price_change_percentage_24h": -3.90199,
      "image": "https://coin-images.coingecko.com/coins/images/33566/large/dogwifhat.jpg?1702499428",
      "last_updated": "2025-09-04T16:27:50.651Z"
    },
    {
      "id": "pendle",
      "symbol": "PENDLE",
      "name": "Pendle",
      "current_price": 4.52,
      "market_cap": 765299248,
      "market_cap_rank": 137,
      "total_volume": 86604297,
      "price_change_percentage_24h": -5.13229,
      "image": "https://coin-images.coingecko.com/coins/images/15069/large/Pendle_Logo_Normal-03.png?1696514728",
      "last_updated": "2025-09-04T16:27:50.114Z"
    },
    {
      "id": "fartcoin",
      "symbol": "FARTCOIN",
      "name": "Fartcoin",
      "current_price": 0.744751,
      "market_cap": 745488575,
      "market_cap_rank": 140,
      "total_volume": 128839105,
      "price_change_percentage_24h": -7.65325,
      "image": "https://coin-images.coingecko.com/coins/images/50891/large/fart.jpg?1729503972",
      "last_updated": "2025-09-04T16:27:50.087Z"
    },
    {
      "id": "ethereum-name-service",
      "symbol": "ENS",
      "name": "Ethereum Name Service",
      "current_price": 22.05,
      "market_cap": 731135149,
      "market_cap_rank": 143,
      "total_volume": 38770393,
      "price_change_percentage_24h": -4.18984,
      "image": "https://coin-images.coingecko.com/coins/images/19785/large/ENS.jpg?1727872989",
      "last_updated": "2025-09-04T16:27:50.068Z"
    },
    {
      "id": "gala",
      "symbol": "GALA",
      "name": "GALA",
      "current_price": 0.01556529,
      "market_cap": 713866318,
      "market_cap_rank": 145,
      "total_volume": 58555513,
      "price_change_percentage_24h": -4.61981,
      "image": "https://coin-images.coingecko.com/coins/images/12493/large/GALA_token_image_-_200PNG.png?1709725869",
      "last_updated": "2025-09-04T16:27:49.760Z"
    },
    {
      "id": "ripple-usd",
      "symbol": "RLUSD",
      "name": "Ripple USD",
      "current_price": 0.999441,
      "market_cap": 709533293,
      "market_cap_rank": 146,
      "total_volume": 42434729,
      "price_change_percentage_24h": -0.05702,
      "image": "https://coin-images.coingecko.com/coins/images/39651/large/RLUSD_200x200_%281%29.png?1727376633",
      "last_updated": "2025-09-04T16:27:49.660Z"
    },
    {
      "id": "jito-governance-token",
      "symbol": "JTO",
      "name": "Jito",
      "current_price": 1.85,
      "market_cap": 695113074,
      "market_cap_rank": 147,
      "total_volume": 29832540,
      "price_change_percentage_24h": -2.17549,
      "image": "https://coin-images.coingecko.com/coins/images/33228/large/jto.png?1701137022",
      "last_updated": "2025-09-04T16:27:49.797Z"
    },
    {
      "id": "virtual-protocol",
      "symbol": "VIRTUAL",
      "name": "Virtuals Protocol",
      "current_price": 1.045,
      "market_cap": 684775744,
      "market_cap_rank": 148,
      "total_volume": 116984572,
      "price_change_percentage_24h": -8.747,
      "image": "https://coin-images.coingecko.com/coins/images/34057/large/LOGOMARK.png?1708356054",
      "last_updated": "2025-09-04T16:27:50.071Z"
    },
    {
      "id": "the-sandbox",
      "symbol": "SAND",
      "name": "The Sandbox",
      "current_price": 0.272063,
      "market_cap": 666105956,
      "market_cap_rank": 151,
      "total_volume": 34109409,
      "price_change_percentage_24h": -4.00895,
      "image": "https://coin-images.coingecko.com/coins/images/12129/large/sandbox_logo.jpg?1696511971",
      "last_updated": "2025-09-04T16:27:49.893Z"
    },
    {
      "id": "morpho",
      "symbol": "MORPHO",
      "name": "Morpho",
      "current_price": 2.01,
      "market_cap": 665225345,
      "market_cap_rank": 152,
      "total_volume": 44933523,
      "price_change_percentage_24h": 1.68564,
      "image": "https://coin-images.coingecko.com/coins/images/29837/large/Morpho-token-icon.png?1726771230",
      "last_updated": "2025-09-04T16:27:49.664Z"
    },
    {
      "id": "zcash",
      "symbol": "ZEC",
      "name": "Zcash",
      "current_price": 40.43,
      "market_cap": 657309539,
      "market_cap_rank": 156,
      "total_volume": 86590664,
      "price_change_percentage_24h": -5.55781,
      "image": "https://coin-images.coingecko.com/coins/images/486/large/circle-zcash-color.png?1696501740",
      "last_updated": "2025-09-04T16:27:49.643Z"
    },
    {
      "id": "arbitrum-bridged-weth-arbitrum-one",
      "symbol": "WETH",
      "name": "Arbitrum Bridged WETH (Arbitrum One)",
      "current_price": 4295.67,
      "market_cap": 648198081,
      "market_cap_rank": 157,
      "total_volume": 401668396,
      "price_change_percentage_24h": -3.73726,
      "image": "https://coin-images.coingecko.com/coins/images/39713/large/WETH.PNG?1723731496",
      "last_updated": "2025-09-04T16:27:50.440Z"
    },
    {
      "id": "walrus-2",
      "symbol": "WAL",
      "name": "Walrus",
      "current_price": 0.408001,
      "market_cap": 590180798,
      "market_cap_rank": 165,
      "total_volume": 22678837,
      "price_change_percentage_24h": -4.99473,
      "image": "https://coin-images.coingecko.com/coins/images/54914/large/WAL_logo.png?1742494301",
      "last_updated": "2025-09-04T16:27:39.375Z"
    },
    {
      "id": "decentraland",
      "symbol": "MANA",
      "name": "Decentraland",
      "current_price": 0.298524,
      "market_cap": 573042962,
      "market_cap_rank": 166,
      "total_volume": 34374122,
      "price_change_percentage_24h": -3.77898,
      "image": "https://coin-images.coingecko.com/coins/images/878/large/decentraland-mana.png?1696502010",
      "last_updated": "2025-09-04T16:27:50.287Z"
    },
    {
      "id": "global-dollar",
      "symbol": "USDG",
      "name": "Global Dollar",
      "current_price": 0.999635,
      "market_cap": 559884679,
      "market_cap_rank": 169,
      "total_volume": 23796274,
      "price_change_percentage_24h": -0.01677,
      "image": "https://coin-images.coingecko.com/coins/images/51281/large/GDN_USDG_Token_200x200.png?1730484111",
      "last_updated": "2025-09-04T16:27:50.021Z"
    },
    {
      "id": "syrup",
      "symbol": "SYRUP",
      "name": "Maple Finance",
      "current_price": 0.47519,
      "market_cap": 530965422,
      "market_cap_rank": 172,
      "total_volume": 76640459,
      "price_change_percentage_24h": -4.11674,
      "image": "https://coin-images.coingecko.com/coins/images/51232/large/_syrup_token_logo.png?1747292046",
      "last_updated": "2025-09-04T16:27:50.088Z"
    },
    {
      "id": "bitcoin-avalanche-bridged-btc-b",
      "symbol": "BTC.B",
      "name": "Avalanche Bridged BTC (Avalanche)",
      "current_price": 109449,
      "market_cap": 526705752,
      "market_cap_rank": 173,
      "total_volume": 63376274,
      "price_change_percentage_24h": -2.28882,
      "image": "https://coin-images.coingecko.com/coins/images/26115/large/btcb.png?1696525205",
      "last_updated": "2025-09-04T16:27:49.701Z"
    },
    {
      "id": "ether-fi",
      "symbol": "ETHFI",
      "name": "Ether.fi",
      "current_price": 1.083,
      "market_cap": 505426354,
      "market_cap_rank": 176,
      "total_volume": 68908995,
      "price_change_percentage_24h": -5.23077,
      "image": "https://coin-images.coingecko.com/coins/images/35958/large/etherfi.jpeg?1710254562",
      "last_updated": "2025-09-04T16:27:39.901Z"
    },
    {
      "id": "starknet",
      "symbol": "STRK",
      "name": "Starknet",
      "current_price": 0.120041,
      "market_cap": 489538911,
      "market_cap_rank": 178,
      "total_volume": 21980660,
      "price_change_percentage_24h": -4.0197,
      "image": "https://coin-images.coingecko.com/coins/images/26433/large/starknet.png?1696525507",
      "last_updated": "2025-09-04T16:27:50.182Z"
    },
    {
      "id": "neo",
      "symbol": "NEO",
      "name": "NEO",
      "current_price": 6.38,
      "market_cap": 450060606,
      "market_cap_rank": 184,
      "total_volume": 24117985,
      "price_change_percentage_24h": -4.10141,
      "image": "https://coin-images.coingecko.com/coins/images/480/large/NEO_512_512.png?1696501735",
      "last_updated": "2025-09-04T16:27:39.744Z"
    },
    {
      "id": "apecoin",
      "symbol": "APE",
      "name": "ApeCoin",
      "current_price": 0.559889,
      "market_cap": 447743672,
      "market_cap_rank": 187,
      "total_volume": 20906960,
      "price_change_percentage_24h": -3.38613,
      "image": "https://coin-images.coingecko.com/coins/images/24383/large/APECOIN.png?1756551529",
      "last_updated": "2025-09-04T16:27:49.857Z"
    },
    {
      "id": "based-brett",
      "symbol": "BRETT",
      "name": "Brett",
      "current_price": 0.0429257,
      "market_cap": 427088134,
      "market_cap_rank": 195,
      "total_volume": 23694540,
      "price_change_percentage_24h": -7.34828,
      "image": "https://coin-images.coingecko.com/coins/images/35529/large/1000050750.png?1709031995",
      "last_updated": "2025-09-04T16:27:50.217Z"
    },
    {
      "id": "thorchain",
      "symbol": "RUNE",
      "name": "THORChain",
      "current_price": 1.17,
      "market_cap": 411960668,
      "market_cap_rank": 203,
      "total_volume": 33960710,
      "price_change_percentage_24h": -3.8817,
      "image": "https://coin-images.coingecko.com/coins/images/6595/large/Rune200x200.png?1696506946",
      "last_updated": "2025-09-04T16:27:50.066Z"
    },
    {
      "id": "arweave",
      "symbol": "AR",
      "name": "Arweave",
      "current_price": 6.24,
      "market_cap": 408584939,
      "market_cap_rank": 205,
      "total_volume": 23420941,
      "price_change_percentage_24h": -3.69386,
      "image": "https://coin-images.coingecko.com/coins/images/4343/large/oRt6SiEN_400x400.jpg?1696504946",
      "last_updated": "2025-09-04T16:27:50.321Z"
    },
    {
      "id": "compound-governance-token",
      "symbol": "COMP",
      "name": "Compound",
      "current_price": 41.88,
      "market_cap": 396214074,
      "market_cap_rank": 208,
      "total_volume": 23139188,
      "price_change_percentage_24h": -4.09881,
      "image": "https://coin-images.coingecko.com/coins/images/10775/large/COMP.png?1696510737",
      "last_updated": "2025-09-04T16:27:39.489Z"
    },
    {
      "id": "eigenlayer",
      "symbol": "EIGEN",
      "name": "EigenCloud (prev. EigenLayer)",
      "current_price": 1.18,
      "market_cap": 389231376,
      "market_cap_rank": 212,
      "total_volume": 45384480,
      "price_change_percentage_24h": -4.41592,
      "image": "https://coin-images.coingecko.com/coins/images/37441/large/eigencloud.jpg?1751003565",
      "last_updated": "2025-09-04T16:27:50.224Z"
    },
    {
      "id": "axie-infinity",
      "symbol": "AXS",
      "name": "Axie Infinity",
      "current_price": 2.31,
      "market_cap": 385442955,
      "market_cap_rank": 213,
      "total_volume": 24728468,
      "price_change_percentage_24h": -4.35479,
      "image": "https://coin-images.coingecko.com/coins/images/13029/large/axie_infinity_logo.png?1696512817",
      "last_updated": "2025-09-04T16:27:50.001Z"
    },
    {
      "id": "chiliz",
      "symbol": "CHZ",
      "name": "Chiliz",
      "current_price": 0.03873071,
      "market_cap": 380681229,
      "market_cap_rank": 215,
      "total_volume": 21862092,
      "price_change_percentage_24h": -3.25673,
      "image": "https://coin-images.coingecko.com/coins/images/8834/large/CHZ_Token_updated.png?1696508986",
      "last_updated": "2025-09-04T16:27:39.855Z"
    },
    {
      "id": "wrapped-avax",
      "symbol": "WAVAX",
      "name": "Wrapped AVAX",
      "current_price": 24.66,
      "market_cap": 373425927,
      "market_cap_rank": 217,
      "total_volume": 263806264,
      "price_change_percentage_24h": -2.86782,
      "image": "https://coin-images.coingecko.com/coins/images/15075/large/wrapped-avax.png?1696514734",
      "last_updated": "2025-09-04T16:27:50.247Z"
    },
    {
      "id": "unit-bitcoin",
      "symbol": "UBTC",
      "name": "Unit Bitcoin",
      "current_price": 109488,
      "market_cap": 358292884,
      "market_cap_rank": 221,
      "total_volume": 44604296,
      "price_change_percentage_24h": -2.38679,
      "image": "https://coin-images.coingecko.com/coins/images/55066/large/ubtc.jpg?1743580113",
      "last_updated": "2025-09-04T16:27:50.050Z"
    },
    {
      "id": "wrapped-hype",
      "symbol": "WHYPE",
      "name": "Wrapped HYPE",
      "current_price": 45.11,
      "market_cap": 354775974,
      "market_cap_rank": 223,
      "total_volume": 146966694,
      "price_change_percentage_24h": -2.00221,
      "image": "https://coin-images.coingecko.com/coins/images/54469/large/_UP3jBsi_400x400.jpg?1739905920",
      "last_updated": "2025-09-04T16:27:50.505Z"
    },
    {
      "id": "livepeer",
      "symbol": "LPT",
      "name": "Livepeer",
      "current_price": 6.59,
      "market_cap": 290154273,
      "market_cap_rank": 256,
      "total_volume": 69107290,
      "price_change_percentage_24h": -3.41923,
      "image": "https://coin-images.coingecko.com/coins/images/7137/large/badge-logo-circuit-green.png?1719357686",
      "last_updated": "2025-09-04T16:27:50.192Z"
    },
    {
      "id": "qtum",
      "symbol": "QTUM",
      "name": "Qtum",
      "current_price": 2.74,
      "market_cap": 289665637,
      "market_cap_rank": 255,
      "total_volume": 148646695,
      "price_change_percentage_24h": 2.70048,
      "image": "https://coin-images.coingecko.com/coins/images/684/large/Qtum_Logo_blue_CG.png?1696501874",
      "last_updated": "2025-09-04T16:27:50.431Z"
    },
    {
      "id": "dash",
      "symbol": "DASH",
      "name": "Dash",
      "current_price": 23.28,
      "market_cap": 288925202,
      "market_cap_rank": 257,
      "total_volume": 20294283,
      "price_change_percentage_24h": -2.26589,
      "image": "https://coin-images.coingecko.com/coins/images/19/large/dash-logo.png?1696501423",
      "last_updated": "2025-09-04T16:27:50.299Z"
    },
    {
      "id": "berachain-bera",
      "symbol": "BERA",
      "name": "Berachain",
      "current_price": 2.15,
      "market_cap": 270296174,
      "market_cap_rank": 267,
      "total_volume": 47557637,
      "price_change_percentage_24h": -8.79773,
      "image": "https://coin-images.coingecko.com/coins/images/25235/large/BERA.png?1738822008",
      "last_updated": "2025-09-04T16:27:50.339Z"
    },
    {
      "id": "bio-protocol",
      "symbol": "BIO",
      "name": "Bio Protocol",
      "current_price": 0.12961,
      "market_cap": 266327834,
      "market_cap_rank": 269,
      "total_volume": 74790373,
      "price_change_percentage_24h": -10.38936,
      "image": "https://coin-images.coingecko.com/coins/images/53022/large/bio.jpg?1735011002",
      "last_updated": "2025-09-04T16:27:50.247Z"
    },
    {
      "id": "turbo",
      "symbol": "TURBO",
      "name": "Turbo",
      "current_price": 0.00365577,
      "market_cap": 252602297,
      "market_cap_rank": 278,
      "total_volume": 21458644,
      "price_change_percentage_24h": -6.37014,
      "image": "https://coin-images.coingecko.com/coins/images/30117/large/TurboMark-QL_200.png?1708079597",
      "last_updated": "2025-09-04T16:27:50.408Z"
    },
    {
      "id": "frax-share",
      "symbol": "FRAX",
      "name": "Frax (prev. FXS)",
      "current_price": 2.71,
      "market_cap": 244077912,
      "market_cap_rank": 284,
      "total_volume": 25994972,
      "price_change_percentage_24h": 3.85973,
      "image": "https://coin-images.coingecko.com/coins/images/13423/large/frax.png?1745921071",
      "last_updated": "2025-09-04T16:27:50.583Z"
    },
    {
      "id": "euro-coin",
      "symbol": "EURC",
      "name": "EURC",
      "current_price": 1.16,
      "market_cap": 237998214,
      "market_cap_rank": 287,
      "total_volume": 39046337,
      "price_change_percentage_24h": -0.26932,
      "image": "https://coin-images.coingecko.com/coins/images/26045/large/euro.png?1696525125",
      "last_updated": "2025-09-04T16:27:50.636Z"
    },
    {
      "id": "kaito",
      "symbol": "KAITO",
      "name": "KAITO",
      "current_price": 0.981005,
      "market_cap": 237088459,
      "market_cap_rank": 290,
      "total_volume": 26222199,
      "price_change_percentage_24h": -6.50246,
      "image": "https://coin-images.coingecko.com/coins/images/54411/large/Qm4DW488_400x400.jpg?1739552780",
      "last_updated": "2025-09-04T16:27:50.281Z"
    },
    {
      "id": "plume",
      "symbol": "PLUME",
      "name": "Plume",
      "current_price": 0.078727,
      "market_cap": 231133306,
      "market_cap_rank": 295,
      "total_volume": 39070913,
      "price_change_percentage_24h": -2.77652,
      "image": "https://coin-images.coingecko.com/coins/images/53623/large/plume-token.png?1736896935",
      "last_updated": "2025-09-04T16:27:50.374Z"
    },
    {
      "id": "popcat",
      "symbol": "POPCAT",
      "name": "Popcat",
      "current_price": 0.234811,
      "market_cap": 230409620,
      "market_cap_rank": 296,
      "total_volume": 22447207,
      "price_change_percentage_24h": -7.57059,
      "image": "https://coin-images.coingecko.com/coins/images/33760/large/image.jpg?1702964227",
      "last_updated": "2025-09-04T16:27:50.447Z"
    },
    {
      "id": "velo",
      "symbol": "VELO",
      "name": "Velo",
      "current_price": 0.01292528,
      "market_cap": 227293917,
      "market_cap_rank": 300,
      "total_volume": 21238085,
      "price_change_percentage_24h": -4.11295,
      "image": "https://coin-images.coingecko.com/coins/images/12538/large/Logo_200x_200.png?1696512350",
      "last_updated": "2025-09-04T16:27:50.458Z"
    },
    {
      "id": "0x",
      "symbol": "ZRX",
      "name": "0x Protocol",
      "current_price": 0.263085,
      "market_cap": 223198095,
      "market_cap_rank": 304,
      "total_volume": 33413244,
      "price_change_percentage_24h": -6.4632,
      "image": "https://coin-images.coingecko.com/coins/images/863/large/0x.png?1696501996",
      "last_updated": "2025-09-04T16:27:50.467Z"
    },
    {
      "id": "arkham",
      "symbol": "ARKM",
      "name": "Arkham",
      "current_price": 0.460089,
      "market_cap": 220306590,
      "market_cap_rank": 308,
      "total_volume": 27751422,
      "price_change_percentage_24h": -5.28089,
      "image": "https://coin-images.coingecko.com/coins/images/30929/large/Arkham_Logo_CG.png?1696529771",
      "last_updated": "2025-09-04T16:27:50.572Z"
    },
    {
      "id": "zora",
      "symbol": "ZORA",
      "name": "Zora",
      "current_price": 0.067154,
      "market_cap": 218282772,
      "market_cap_rank": 309,
      "total_volume": 60808909,
      "price_change_percentage_24h": -12.54383,
      "image": "https://coin-images.coingecko.com/coins/images/54693/large/zora.jpg?1741094751",
      "last_updated": "2025-09-04T16:27:50.834Z"
    },
    {
      "id": "grass",
      "symbol": "GRASS",
      "name": "Grass",
      "current_price": 0.699153,
      "market_cap": 215044321,
      "market_cap_rank": 314,
      "total_volume": 24010983,
      "price_change_percentage_24h": -4.71891,
      "image": "https://coin-images.coingecko.com/coins/images/40094/large/Grass.jpg?1725697048",
      "last_updated": "2025-09-04T16:27:50.575Z"
    },
    {
      "id": "mantra-dao",
      "symbol": "OM",
      "name": "MANTRA",
      "current_price": 0.197894,
      "market_cap": 209826460,
      "market_cap_rank": 317,
      "total_volume": 36743065,
      "price_change_percentage_24h": -4.04566,
      "image": "https://coin-images.coingecko.com/coins/images/12151/large/OM_Token.png?1696511991",
      "last_updated": "2025-09-04T16:27:50.744Z"
    },
    {
      "id": "bridged-usd-coin-linea",
      "symbol": "USDC",
      "name": "Bridged USD Coin (Linea)",
      "current_price": 0.998721,
      "market_cap": 202291151,
      "market_cap_rank": 323,
      "total_volume": 105991592,
      "price_change_percentage_24h": -0.12128,
      "image": "https://coin-images.coingecko.com/coins/images/31270/large/USDC-icon.png?1696530094",
      "last_updated": "2025-09-04T16:27:50.479Z"
    },
    {
      "id": "layerzero",
      "symbol": "ZRO",
      "name": "LayerZero",
      "current_price": 1.82,
      "market_cap": 202254211,
      "market_cap_rank": 324,
      "total_volume": 21248478,
      "price_change_percentage_24h": -3.7788,
      "image": "https://coin-images.coingecko.com/coins/images/28206/large/ftxG9_TJ_400x400.jpeg?1696527208",
      "last_updated": "2025-09-04T16:27:50.586Z"
    },
    {
      "id": "sahara-ai",
      "symbol": "SAHARA",
      "name": "Sahara AI",
      "current_price": 0.089964,
      "market_cap": 198736648,
      "market_cap_rank": 325,
      "total_volume": 21673394,
      "price_change_percentage_24h": -3.74765,
      "image": "https://coin-images.coingecko.com/coins/images/66681/large/Token_Logo_3x.png?1750362133",
      "last_updated": "2025-09-04T16:27:50.442Z"
    },
    {
      "id": "peanut-the-squirrel",
      "symbol": "PNUT",
      "name": "Peanut the Squirrel",
      "current_price": 0.197944,
      "market_cap": 197868916,
      "market_cap_rank": 326,
      "total_volume": 40262076,
      "price_change_percentage_24h": -4.72598,
      "image": "https://coin-images.coingecko.com/coins/images/51301/large/Peanut_the_Squirrel.png?1734941241",
      "last_updated": "2025-09-04T16:27:51.874Z"
    },
    {
      "id": "troll-2",
      "symbol": "TROLL",
      "name": "TROLL",
      "current_price": 0.192907,
      "market_cap": 192332504,
      "market_cap_rank": 334,
      "total_volume": 41307729,
      "price_change_percentage_24h": 16.14883,
      "image": "https://coin-images.coingecko.com/coins/images/55282/large/trolllogo.png?1745215015",
      "last_updated": "2025-09-04T16:27:50.647Z"
    },
    {
      "id": "ordinals",
      "symbol": "ORDI",
      "name": "ORDI",
      "current_price": 8.58,
      "market_cap": 180594772,
      "market_cap_rank": 340,
      "total_volume": 28687941,
      "price_change_percentage_24h": -1.94762,
      "image": "https://coin-images.coingecko.com/coins/images/30162/large/ordi.png?1696529082",
      "last_updated": "2025-09-04T16:27:50.571Z"
    },
    {
      "id": "notcoin",
      "symbol": "NOT",
      "name": "Notcoin",
      "current_price": 0.00180683,
      "market_cap": 179742859,
      "market_cap_rank": 344,
      "total_volume": 20374461,
      "price_change_percentage_24h": -3.32907,
      "image": "https://coin-images.coingecko.com/coins/images/33453/large/rFmThDiD_400x400.jpg?1701876350",
      "last_updated": "2025-09-04T16:27:50.571Z"
    },
    {
      "id": "reallink",
      "symbol": "REAL",
      "name": "RealLink",
      "current_price": 0.058799,
      "market_cap": 170126367,
      "market_cap_rank": 352,
      "total_volume": 28738937,
      "price_change_percentage_24h": -3.4724,
      "image": "https://coin-images.coingecko.com/coins/images/20665/large/TGBfBt6Y2Dm3RHdNpZAdqywBsvfdysf834.jpeg?1749135788",
      "last_updated": "2025-09-04T16:27:50.489Z"
    },
    {
      "id": "succinct",
      "symbol": "PROVE",
      "name": "Succinct",
      "current_price": 0.862318,
      "market_cap": 168210369,
      "market_cap_rank": 354,
      "total_volume": 68897214,
      "price_change_percentage_24h": -10.26265,
      "image": "https://coin-images.coingecko.com/coins/images/67905/large/succinct-logo.png?1754228574",
      "last_updated": "2025-09-04T16:27:50.911Z"
    },
    {
      "id": "skale",
      "symbol": "SKL",
      "name": "SKALE",
      "current_price": 0.02879198,
      "market_cap": 166350271,
      "market_cap_rank": 359,
      "total_volume": 38100028,
      "price_change_percentage_24h": -3.62996,
      "image": "https://coin-images.coingecko.com/coins/images/13245/large/SKALE_token_300x300.png?1696513021",
      "last_updated": "2025-09-04T16:27:50.650Z"
    },
    {
      "id": "bnb48-club-token",
      "symbol": "KOGE",
      "name": "KOGE",
      "current_price": 48.0,
      "market_cap": 162257605,
      "market_cap_rank": 366,
      "total_volume": 617398303,
      "price_change_percentage_24h": -0.03058,
      "image": "https://coin-images.coingecko.com/coins/images/13827/large/bnb48.png?1696513570",
      "last_updated": "2025-09-04T16:27:50.607Z"
    },
    {
      "id": "useless-3",
      "symbol": "USELESS",
      "name": "Useless Coin",
      "current_price": 0.16058,
      "market_cap": 160984361,
      "market_cap_rank": 369,
      "total_volume": 20059932,
      "price_change_percentage_24h": -7.57815,
      "image": "https://coin-images.coingecko.com/coins/images/55684/large/coingeckoupdate.png?1755203747",
      "last_updated": "2025-09-04T16:27:50.692Z"
    },
    {
      "id": "merlin-chain",
      "symbol": "MERL",
      "name": "Merlin Chain",
      "current_price": 0.162355,
      "market_cap": 152772513,
      "market_cap_rank": 378,
      "total_volume": 49199796,
      "price_change_percentage_24h": 4.50623,
      "image": "https://coin-images.coingecko.com/coins/images/37118/large/merlin.jpeg?1713352230",
      "last_updated": "2025-09-04T16:27:50.974Z"
    },
    {
      "id": "camp-network",
      "symbol": "CAMP",
      "name": "Camp Network",
      "current_price": 0.071514,
      "market_cap": 151147635,
      "market_cap_rank": 379,
      "total_volume": 191017612,
      "price_change_percentage_24h": -14.12535,
      "image": "https://coin-images.coingecko.com/coins/images/68465/large/camp.png?1755828258",
      "last_updated": "2025-09-04T16:27:50.833Z"
    },
    {
      "id": "myx-finance",
      "symbol": "MYX",
      "name": "MYX Finance",
      "current_price": 1.15,
      "market_cap": 143956041,
      "market_cap_rank": 389,
      "total_volume": 20855049,
      "price_change_percentage_24h": -0.46288,
      "image": "https://coin-images.coingecko.com/coins/images/55506/large/myx.jpg?1746434335",
      "last_updated": "2025-09-04T16:27:50.750Z"
    },
    {
      "id": "sushi",
      "symbol": "SUSHI",
      "name": "Sushi",
      "current_price": 0.742024,
      "market_cap": 143127032,
      "market_cap_rank": 393,
      "total_volume": 21818013,
      "price_change_percentage_24h": -5.22739,
      "image": "https://coin-images.coingecko.com/coins/images/12271/large/512x512_Logo_no_chop.png?1696512101",
      "last_updated": "2025-09-04T16:27:50.888Z"
    },
    {
      "id": "neiro-3",
      "symbol": "NEIRO",
      "name": "Neiro",
      "current_price": 0.00032401,
      "market_cap": 136400390,
      "market_cap_rank": 400,
      "total_volume": 31389789,
      "price_change_percentage_24h": -5.04637,
      "image": "https://coin-images.coingecko.com/coins/images/39488/large/neiro.jpg?1731449567",
      "last_updated": "2025-09-04T16:27:50.790Z"
    },
    {
      "id": "memecoin-2",
      "symbol": "MEME",
      "name": "Memecoin",
      "current_price": 0.00239182,
      "market_cap": 131428293,
      "market_cap_rank": 413,
      "total_volume": 38020500,
      "price_change_percentage_24h": -7.2448,
      "image": "https://coin-images.coingecko.com/coins/images/32528/large/memecoin_%282%29.png?1698912168",
      "last_updated": "2025-09-04T16:27:50.850Z"
    },
    {
      "id": "avalanche-bridged-weth-avalanche",
      "symbol": "WETH",
      "name": "Avalanche Bridged WETH (Avalanche)",
      "current_price": 4302.36,
      "market_cap": 129244256,
      "market_cap_rank": 421,
      "total_volume": 67732958,
      "price_change_percentage_24h": -3.71538,
      "image": "https://coin-images.coingecko.com/coins/images/39707/large/WETH.PNG?1723730205",
      "last_updated": "2025-09-04T16:27:50.867Z"
    },
    {
      "id": "book-of-meme",
      "symbol": "BOME",
      "name": "BOOK OF MEME",
      "current_price": 0.00185601,
      "market_cap": 128187444,
      "market_cap_rank": 426,
      "total_volume": 25410043,
      "price_change_percentage_24h": -4.77333,
      "image": "https://coin-images.coingecko.com/coins/images/36071/large/bome.png?1710407255",
      "last_updated": "2025-09-04T16:27:51.062Z"
    },
    {
      "id": "stepn",
      "symbol": "GMT",
      "name": "GMT",
      "current_price": 0.04005003,
      "market_cap": 127076133,
      "market_cap_rank": 428,
      "total_volume": 21682343,
      "price_change_percentage_24h": -4.75923,
      "image": "https://coin-images.coingecko.com/coins/images/23597/large/token-gmt-200x200.png?1703153841",
      "last_updated": "2025-09-04T16:27:51.079Z"
    },
    {
      "id": "moo-deng",
      "symbol": "MOODENG",
      "name": "Moo Deng",
      "current_price": 0.126257,
      "market_cap": 125122776,
      "market_cap_rank": 432,
      "total_volume": 21441825,
      "price_change_percentage_24h": -5.29011,
      "image": "https://coin-images.coingecko.com/coins/images/50264/large/MOODENG.jpg?1726726975",
      "last_updated": "2025-09-04T16:27:51.030Z"
    },
    {
      "id": "api3",
      "symbol": "API3",
      "name": "Api3",
      "current_price": 0.967229,
      "market_cap": 124296168,
      "market_cap_rank": 434,
      "total_volume": 27259650,
      "price_change_percentage_24h": -6.06372,
      "image": "https://coin-images.coingecko.com/coins/images/13256/large/Api3-Token.png?1742439807",
      "last_updated": "2025-09-04T16:27:51.049Z"
    },
    {
      "id": "loopring",
      "symbol": "LRC",
      "name": "Loopring",
      "current_price": 0.098664,
      "market_cap": 122939739,
      "market_cap_rank": 440,
      "total_volume": 29297669,
      "price_change_percentage_24h": -5.08571,
      "image": "https://coin-images.coingecko.com/coins/images/913/large/LRC.png?1696502034",
      "last_updated": "2025-09-04T16:27:51.091Z"
    },
    {
      "id": "babylon",
      "symbol": "BABY",
      "name": "Babylon",
      "current_price": 0.04437744,
      "market_cap": 115777576,
      "market_cap_rank": 453,
      "total_volume": 22853936,
      "price_change_percentage_24h": -5.32574,
      "image": "https://coin-images.coingecko.com/coins/images/55092/large/Baby-Symbol-Mint_%281%29.png?1744788866",
      "last_updated": "2025-09-04T16:27:51.062Z"
    },
    {
      "id": "redstone-oracles",
      "symbol": "RED",
      "name": "RedStone",
      "current_price": 0.408623,
      "market_cap": 114780952,
      "market_cap_rank": 455,
      "total_volume": 76177488,
      "price_change_percentage_24h": -1.07753,
      "image": "https://coin-images.coingecko.com/coins/images/53640/large/RedStone_Logo_New_White.png?1740640919",
      "last_updated": "2025-09-04T16:27:51.277Z"
    },
    {
      "id": "wilder-world",
      "symbol": "WILD",
      "name": "Wilder World",
      "current_price": 0.281702,
      "market_cap": 111228122,
      "market_cap_rank": 469,
      "total_volume": 21566467,
      "price_change_percentage_24h": 13.77957,
      "image": "https://coin-images.coingecko.com/coins/images/15407/large/wld-logo.png?1712273448",
      "last_updated": "2025-09-04T16:27:51.218Z"
    },
    {
      "id": "revox",
      "symbol": "REX",
      "name": "REVOX",
      "current_price": 0.05243,
      "market_cap": 104262975,
      "market_cap_rank": 489,
      "total_volume": 24673529,
      "price_change_percentage_24h": 15.54984,
      "image": "https://coin-images.coingecko.com/coins/images/52909/large/RREVOX_LOG.png?1734647416",
      "last_updated": "2025-09-04T16:27:51.206Z"
    },
    {
      "id": "io",
      "symbol": "IO",
      "name": "io.net",
      "current_price": 0.513413,
      "market_cap": 103368710,
      "market_cap_rank": 491,
      "total_volume": 33115269,
      "price_change_percentage_24h": -5.49473,
      "image": "https://coin-images.coingecko.com/coins/images/37754/large/io_blackbg.png?1715446363",
      "last_updated": "2025-09-04T16:27:51.314Z"
    }
  ],
  "metadata": {
    "total_coins": 174,
    "updated_at": "2025-09-04T16:28:03.926022",
    "filter_criteria": {
      "min_market_cap": 100000000,
      "min_volume_24h": 20000000,
      "max_pages": 2,
      "blocked_coins_count": 25
    },
    "filter_stats": {
      "Low volume": 317,
      "Blocked": 5,
      "Invalid symbol": 4
    },
    "api_source": "CoinGecko Standard API"
  }
}